{
  "key": "doi-10.1016_j.concog.2021.103140",
  "data": {
    "indexed": {
      "date-parts": [
        [
          2025,
          10,
          21
        ]
      ],
      "date-time": "2025-10-21T00:29:24Z",
      "timestamp": 1761006564447,
      "version": "build-2065373602"
    },
    "reference-count": 82,
    "publisher": "Elsevier BV",
    "license": [
      {
        "start": {
          "date-parts": [
            [
              2021,
              7,
              1
            ]
          ],
          "date-time": "2021-07-01T00:00:00Z",
          "timestamp": 1625097600000
        },
        "content-version": "tdm",
        "delay-in-days": 0,
        "URL": "https://www.elsevier.com/tdm/userlicense/1.0/"
      },
      {
        "start": {
          "date-parts": [
            [
              2021,
              7,
              1
            ]
          ],
          "date-time": "2021-07-01T00:00:00Z",
          "timestamp": 1625097600000
        },
        "content-version": "tdm",
        "delay-in-days": 0,
        "URL": "https://www.elsevier.com/legal/tdmrep-license"
      },
      {
        "start": {
          "date-parts": [
            [
              2021,
              7,
              1
            ]
          ],
          "date-time": "2021-07-01T00:00:00Z",
          "timestamp": 1625097600000
        },
        "content-version": "stm-asf",
        "delay-in-days": 0,
        "URL": "https://doi.org/10.15223/policy-017"
      },
      {
        "start": {
          "date-parts": [
            [
              2021,
              7,
              1
            ]
          ],
          "date-time": "2021-07-01T00:00:00Z",
          "timestamp": 1625097600000
        },
        "content-version": "stm-asf",
        "delay-in-days": 0,
        "URL": "https://doi.org/10.15223/policy-037"
      },
      {
        "start": {
          "date-parts": [
            [
              2021,
              7,
              1
            ]
          ],
          "date-time": "2021-07-01T00:00:00Z",
          "timestamp": 1625097600000
        },
        "content-version": "stm-asf",
        "delay-in-days": 0,
        "URL": "https://doi.org/10.15223/policy-012"
      },
      {
        "start": {
          "date-parts": [
            [
              2021,
              7,
              1
            ]
          ],
          "date-time": "2021-07-01T00:00:00Z",
          "timestamp": 1625097600000
        },
        "content-version": "stm-asf",
        "delay-in-days": 0,
        "URL": "https://doi.org/10.15223/policy-029"
      },
      {
        "start": {
          "date-parts": [
            [
              2021,
              7,
              1
            ]
          ],
          "date-time": "2021-07-01T00:00:00Z",
          "timestamp": 1625097600000
        },
        "content-version": "stm-asf",
        "delay-in-days": 0,
        "URL": "https://doi.org/10.15223/policy-004"
      }
    ],
    "funder": [
      {
        "DOI": "10.13039/501100002920",
        "name": "University Grants Committee Research Grants Council",
        "doi-asserted-by": "publisher",
        "id": [
          {
            "id": "10.13039/501100002920",
            "id-type": "DOI",
            "asserted-by": "publisher"
          }
        ]
      },
      {
        "DOI": "10.13039/100000874",
        "name": "Brain and Behavior Research Foundation",
        "doi-asserted-by": "publisher",
        "id": [
          {
            "id": "10.13039/100000874",
            "id-type": "DOI",
            "asserted-by": "publisher"
          }
        ]
      }
    ],
    "content-domain": {
      "domain": [
        "elsevier.com",
        "sciencedirect.com"
      ],
      "crossmark-restriction": true
    },
    "short-container-title": [
      "Consciousness and Cognition"
    ],
    "published-print": {
      "date-parts": [
        [
          2021,
          7
        ]
      ]
    },
    "DOI": "10.1016/j.concog.2021.103140",
    "type": "journal-article",
    "created": {
      "date-parts": [
        [
          2021,
          5,
          19
        ]
      ],
      "date-time": "2021-05-19T18:31:38Z",
      "timestamp": 1621449098000
    },
    "page": "103140",
    "update-policy": "https://doi.org/10.1016/elsevier_cm_policy",
    "source": "Crossref",
    "is-referenced-by-count": 3,
    "special_numbering": "C",
    "title": [
      "Visuospatial perspective shifting and relational self-association in dispositional shame and guilt"
    ],
    "prefix": "10.1016",
    "volume": "92",
    "author": [
      {
        "given": "Chui-De",
        "family": "Chiu",
        "sequence": "first",
        "affiliation": []
      },
      {
        "given": "Cheuk Ying",
        "family": "Siu",
        "sequence": "additional",
        "affiliation": []
      },
      {
        "given": "Hau Ching",
        "family": "Ng",
        "sequence": "additional",
        "affiliation": []
      },
      {
        "given": "Mark W.",
        "family": "Baldwin",
        "sequence": "additional",
        "affiliation": []
      }
    ],
    "member": "78",
    "reference": [
      {
        "key": "10.1016/j.concog.2021.103140_b0005",
        "doi-asserted-by": "crossref",
        "first-page": "776",
        "DOI": "10.1002/job.686",
        "article-title": "Best-practice recommendations for estimating interaction effects using moderated multiple regression",
        "volume": "31",
        "author": "Aguinis",
        "year": "2010",
        "journal-title": "Journal of Organizational Behavior"
      },
      {
        "year": "1991",
        "series-title": "Multiple regression: Testing and interpreting interactions",
        "author": "Aiken",
        "key": "10.1016/j.concog.2021.103140_b0010"
      },
      {
        "key": "10.1016/j.concog.2021.103140_b0015",
        "doi-asserted-by": "crossref",
        "first-page": "524",
        "DOI": "10.1111/j.1467-9280.2007.01933.x",
        "article-title": "A dynamic model of guilt: Implications for motivation and self-regulation in the context of prejudice",
        "volume": "18",
        "author": "Amodio",
        "year": "2007",
        "journal-title": "Psychological Science"
      },
      {
        "key": "10.1016/j.concog.2021.103140_b0020",
        "doi-asserted-by": "crossref",
        "first-page": "461",
        "DOI": "10.1037/0033-2909.112.3.461",
        "article-title": "Relational schemas and the processing of social information",
        "volume": "112",
        "author": "Baldwin",
        "year": "1992",
        "journal-title": "Psychological Bulletin"
      },
      {
        "key": "10.1016/j.concog.2021.103140_b0025",
        "doi-asserted-by": "crossref",
        "first-page": "157",
        "DOI": "10.1080/10478400701512703",
        "article-title": "On priming security and insecurity",
        "volume": "18",
        "author": "Baldwin",
        "year": "2007",
        "journal-title": "Psychological Inquiry"
      },
      {
        "key": "10.1016/j.concog.2021.103140_b0030",
        "first-page": "139",
        "article-title": "Maintaining a focus on the social goals underlying self-conscious emotions",
        "volume": "15",
        "author": "Baldwin",
        "year": "2004",
        "journal-title": "Psychological Inquiry"
      },
      {
        "key": "10.1016/j.concog.2021.103140_b0035",
        "doi-asserted-by": "crossref",
        "first-page": "746",
        "DOI": "10.1177/0146167293196010",
        "article-title": "An exploration of the relational schemata underlying attachment styles: Self-report and lexical decision approaches",
        "volume": "19",
        "author": "Baldwin",
        "year": "1993",
        "journal-title": "Personality and Social Psychology Bulletin"
      },
      {
        "key": "10.1016/j.concog.2021.103140_b0040",
        "series-title": "Handbook of implicit social cognition: Measurement, theory, and applications",
        "first-page": "426",
        "article-title": "Measuring implicit processes in close relationships",
        "author": "Baldwin",
        "year": "2010"
      },
      {
        "key": "10.1016/j.concog.2021.103140_b0045",
        "doi-asserted-by": "crossref",
        "first-page": "1130",
        "DOI": "10.1037/0022-3514.71.6.1130",
        "article-title": "Self-esteem and “if… then” contingencies of interpersonal acceptance",
        "volume": "71",
        "author": "Baldwin",
        "year": "1996",
        "journal-title": "Journal of Personality and Social Psychology"
      },
      {
        "key": "10.1016/j.concog.2021.103140_b0050",
        "doi-asserted-by": "crossref",
        "first-page": "668",
        "DOI": "10.3758/s13428-013-0410-6",
        "article-title": "A comparative investigation of seven indirect attitude measures",
        "volume": "46",
        "author": "Bar-Anan",
        "year": "2014",
        "journal-title": "Behavior Research Methods"
      },
      {
        "key": "10.1016/j.concog.2021.103140_b0055",
        "doi-asserted-by": "crossref",
        "first-page": "977",
        "DOI": "10.1002/ejsp.487",
        "article-title": "Reliability and validity of the Single-Target IAT (ST-IAT): Assessing automatic affect towards multiple attitude objects",
        "volume": "38",
        "author": "Bluemke",
        "year": "2008",
        "journal-title": "European Journal of Social Psychology"
      },
      {
        "key": "10.1016/j.concog.2021.103140_b0060",
        "doi-asserted-by": "crossref",
        "first-page": "74",
        "DOI": "10.1016/0749-596X(92)90006-J",
        "article-title": "Internal and external spatial frameworks for representing described scenes",
        "volume": "31",
        "author": "Bryant",
        "year": "1992",
        "journal-title": "Journal of Memory and Language"
      },
      {
        "key": "10.1016/j.concog.2021.103140_b0065",
        "doi-asserted-by": "crossref",
        "first-page": "49",
        "DOI": "10.1016/j.tics.2006.11.004",
        "article-title": "Self-projection and the brain",
        "volume": "11",
        "author": "Buckner",
        "year": "2006",
        "journal-title": "Trends in Cognitive Sciences"
      },
      {
        "key": "10.1016/j.concog.2021.103140_b0070",
        "doi-asserted-by": "crossref",
        "first-page": "365",
        "DOI": "10.1037/a0021341",
        "article-title": "Implicit self-esteem: Nature, measurement, and a new way forward",
        "volume": "100",
        "author": "Buhrmester",
        "year": "2011",
        "journal-title": "Journal of Personality and Social Psychology"
      },
      {
        "key": "10.1016/j.concog.2021.103140_b0075",
        "doi-asserted-by": "crossref",
        "first-page": "182",
        "DOI": "10.1080/17588928.2015.1043879",
        "article-title": "Can emotions influence level-1 visual perspective taking?",
        "volume": "7",
        "author": "Bukowski",
        "year": "2016",
        "journal-title": "Cognitive Neuroscience"
      },
      {
        "key": "10.1016/j.concog.2021.103140_b0080",
        "doi-asserted-by": "crossref",
        "first-page": "78",
        "DOI": "10.1016/j.janxdis.2018.07.005",
        "article-title": "Shame-proneness, guilt-proneness and anxiety symptoms: A meta-analysis",
        "volume": "58",
        "author": "Cândea",
        "year": "2018",
        "journal-title": "Journal of Anxiety Disorders"
      },
      {
        "key": "10.1016/j.concog.2021.103140_b0085",
        "doi-asserted-by": "crossref",
        "first-page": "69",
        "DOI": "10.1177/0956797616672464",
        "article-title": "When far becomes near: Perspective taking induces social remapping of spatial relations",
        "volume": "28",
        "author": "Cavallo",
        "year": "2017",
        "journal-title": "Psychological Science"
      },
      {
        "year": "2002",
        "series-title": "Wechsler adult intelligence scale-third edition (WAIS-III) manual for Taiwan",
        "author": "Chen",
        "key": "10.1016/j.concog.2021.103140_b0090"
      },
      {
        "key": "10.1016/j.concog.2021.103140_b0095",
        "unstructured": "Chiu, C. -D. (2016). [Implicit relational self-association and interpersonal behaviors]. Unpublished data."
      },
      {
        "key": "10.1016/j.concog.2021.103140_b0100",
        "doi-asserted-by": "crossref",
        "first-page": "169",
        "DOI": "10.1177/2167702619863058",
        "article-title": "Feeling empathically toward other people and the self: The role of perspective shifting in emotion sharing and self-reassurance",
        "volume": "8",
        "author": "Chiu",
        "year": "2020",
        "journal-title": "Clinical Psychological Science"
      },
      {
        "key": "10.1016/j.concog.2021.103140_b0105",
        "doi-asserted-by": "crossref",
        "first-page": "39",
        "DOI": "10.1037/emo0000346",
        "article-title": "In your shoes or mine? Shifting from other to self perspective is vital for emotional empathy",
        "volume": "18",
        "author": "Chiu",
        "year": "2018",
        "journal-title": "Emotion"
      },
      {
        "key": "10.1016/j.concog.2021.103140_b0110",
        "doi-asserted-by": "crossref",
        "unstructured": "Chiu, C.-D., Ho, H. L., & Tollenaar, M. S. (2021). Relational self-evaluations in dissociation: Implicit self-rejection? Psychological Trauma: Theory, Research, Practice, and Policy. Advanced online publication. https://doi.org/10.1037/tra0001017.",
        "DOI": "10.1037/tra0001017"
      },
      {
        "key": "10.1016/j.concog.2021.103140_b0115",
        "doi-asserted-by": "crossref",
        "first-page": "64",
        "DOI": "10.1037/tra0000369",
        "article-title": "Early relational trauma and self representations: Misattributing externally derived representations as internally generated",
        "volume": "11",
        "author": "Chiu",
        "year": "2019",
        "journal-title": "Psychological Trauma: Theory, Research, Practice, and Policy"
      },
      {
        "key": "10.1016/j.concog.2021.103140_b0120",
        "first-page": "493",
        "article-title": "Taiwan corpora of Chinese emotions and relevant psychophysiological data: A study on the norm of Chinese emotional words",
        "volume": "55",
        "author": "Cho",
        "year": "2013",
        "journal-title": "Chinese Journal of Psychology"
      },
      {
        "key": "10.1016/j.concog.2021.103140_b0125",
        "doi-asserted-by": "crossref",
        "first-page": "155",
        "DOI": "10.1037/0033-2909.112.1.155",
        "article-title": "A power primer",
        "volume": "112",
        "author": "Cohen",
        "year": "1992",
        "journal-title": "Psychological Bulletin"
      },
      {
        "year": "1983",
        "series-title": "Applied multiple regression/correlation analyses for the behavioral sciences",
        "author": "Cohen",
        "key": "10.1016/j.concog.2021.103140_b0130"
      },
      {
        "key": "10.1016/j.concog.2021.103140_b0135",
        "doi-asserted-by": "crossref",
        "first-page": "947",
        "DOI": "10.1037/a0022641",
        "article-title": "Introducing the GASP scale: A new measure of guilt and shame proneness",
        "volume": "100",
        "author": "Cohen",
        "year": "2011",
        "journal-title": "Journal of Personality and Social Psychology"
      },
      {
        "year": "1902",
        "series-title": "Human nature and the social order",
        "author": "Cooley",
        "key": "10.1016/j.concog.2021.103140_b0140"
      },
      {
        "key": "10.1016/j.concog.2021.103140_b0145",
        "doi-asserted-by": "crossref",
        "first-page": "1902",
        "DOI": "10.1016/j.neuroimage.2007.12.062",
        "article-title": "Effects of shifting perspective of the self: An fMRI study",
        "volume": "40",
        "author": "Corradi-Dell’Acqua",
        "year": "2008",
        "journal-title": "NeuroImage"
      },
      {
        "key": "10.1016/j.concog.2021.103140_b0150",
        "doi-asserted-by": "crossref",
        "first-page": "1",
        "DOI": "10.1007/s10869-013-9308-7",
        "article-title": "Moderation in management research: What, why, when, and how",
        "volume": "29",
        "author": "Dawson",
        "year": "2014",
        "journal-title": "Journal of Business and Psychology"
      },
      {
        "key": "10.1016/j.concog.2021.103140_b0155",
        "series-title": "Psychology of shame: New research",
        "first-page": "95",
        "article-title": "The general sociometer shame: Positive interpersonal consequences of an ugly emotion",
        "author": "de Hooge",
        "year": "2014"
      },
      {
        "key": "10.1016/j.concog.2021.103140_b0160",
        "doi-asserted-by": "crossref",
        "first-page": "933",
        "DOI": "10.1037/a0011991",
        "article-title": "Not so ugly after all: When shame acts as a commitment device",
        "volume": "95",
        "author": "de Hooge",
        "year": "2008",
        "journal-title": "Journal of Personality and Social Psychology"
      },
      {
        "key": "10.1016/j.concog.2021.103140_b0165",
        "doi-asserted-by": "crossref",
        "first-page": "1025",
        "DOI": "10.1080/02699930600980874",
        "article-title": "Moral sentiments and cooperation: Differential influences of shame and guilt",
        "volume": "21",
        "author": "de Hooge",
        "year": "2007",
        "journal-title": "Cognition and Emotion"
      },
      {
        "key": "10.1016/j.concog.2021.103140_b0170",
        "doi-asserted-by": "crossref",
        "first-page": "111",
        "DOI": "10.1080/02699930802584466",
        "article-title": "Restore and protect motivations following shame",
        "volume": "24",
        "author": "de Hooge",
        "year": "2010",
        "journal-title": "Cognition and Emotion"
      },
      {
        "key": "10.1016/j.concog.2021.103140_b0175",
        "doi-asserted-by": "crossref",
        "first-page": "557",
        "DOI": "10.1348/014466607X265148",
        "article-title": "Proximity seeking in adult attachment: Examining the role of automatic approach–avoidance tendencies",
        "volume": "47",
        "author": "Dewitte",
        "year": "2008",
        "journal-title": "British Journal of Social Psychology"
      },
      {
        "key": "10.1016/j.concog.2021.103140_b0180",
        "doi-asserted-by": "crossref",
        "first-page": "1149",
        "DOI": "10.3758/BRM.41.4.1149",
        "article-title": "Statistical power analyses using G* Power 3.1: Tests for correlation and regression analyses",
        "volume": "41",
        "author": "Faul",
        "year": "2009",
        "journal-title": "Behavior Research Methods"
      },
      {
        "key": "10.1016/j.concog.2021.103140_b0185",
        "doi-asserted-by": "crossref",
        "first-page": "183",
        "DOI": "10.1111/j.1750-8606.2011.00177.x",
        "article-title": "Embodied awareness: Neither implicit nor explicit, and not necessarily nonverbal",
        "volume": "5",
        "author": "Fogel",
        "year": "2011",
        "journal-title": "Child Development Perspectives"
      },
      {
        "key": "10.1016/j.concog.2021.103140_b0190",
        "doi-asserted-by": "crossref",
        "first-page": "468",
        "DOI": "10.1002/ejsp.803",
        "article-title": "Concern for self-image and social image in the management of moral failure: Rethinking shame",
        "volume": "41",
        "author": "Gausel",
        "year": "2011",
        "journal-title": "European Journal of Social Psychology"
      },
      {
        "key": "10.1016/j.concog.2021.103140_b0195",
        "series-title": "Cognitive methods in social psychology",
        "first-page": "78",
        "article-title": "Response interference tasks as indirect measures of automatic associations",
        "author": "Gawronski",
        "year": "2011"
      },
      {
        "key": "10.1016/j.concog.2021.103140_b0200",
        "doi-asserted-by": "crossref",
        "first-page": "485",
        "DOI": "10.1016/j.concog.2005.11.007",
        "article-title": "Are “implicit” attitudes unconscious?",
        "volume": "15",
        "author": "Gawronski",
        "year": "2006",
        "journal-title": "Consciousness and Cognition"
      },
      {
        "key": "10.1016/j.concog.2021.103140_b0205",
        "series-title": "The bright side of shame",
        "first-page": "413",
        "article-title": "Distinguishing shame, humiliation and guilt: An evolutionary functional analysis and compassion focused interventions",
        "author": "Gilbert",
        "year": "2019"
      },
      {
        "key": "10.1016/j.concog.2021.103140_b0210",
        "doi-asserted-by": "crossref",
        "first-page": "1022",
        "DOI": "10.1037/0022-3514.79.6.1022",
        "article-title": "Using the implicit association test to measure self-esteem and self-concept",
        "volume": "79",
        "author": "Greenwald",
        "year": "2000",
        "journal-title": "Journal of Personality and Social Psychology"
      },
      {
        "key": "10.1016/j.concog.2021.103140_b0215",
        "doi-asserted-by": "crossref",
        "first-page": "1464",
        "DOI": "10.1037/0022-3514.74.6.1464",
        "article-title": "Measuring individual differences in implicit cognition: The implicit association test",
        "volume": "74",
        "author": "Greenwald",
        "year": "1998",
        "journal-title": "Journal of Personality and Social Psychology"
      },
      {
        "key": "10.1016/j.concog.2021.103140_b0220",
        "doi-asserted-by": "crossref",
        "first-page": "2205",
        "DOI": "10.1016/j.paid.2007.06.032",
        "article-title": "Measuring Big-Five personality dimensions with the implicit association test–Implicit personality traits or self-esteem?",
        "volume": "43",
        "author": "Grumm",
        "year": "2007",
        "journal-title": "Personality and Individual Differences"
      },
      {
        "key": "10.1016/j.concog.2021.103140_b0225",
        "doi-asserted-by": "crossref",
        "first-page": "16",
        "DOI": "10.1037/0022-3514.91.1.16",
        "article-title": "The single category implicit association test as a measure of implicit social cognition",
        "volume": "91",
        "author": "Karpinski",
        "year": "2006",
        "journal-title": "Journal of Personality and Social Psychology"
      },
      {
        "key": "10.1016/j.concog.2021.103140_b0230",
        "doi-asserted-by": "crossref",
        "first-page": "1089",
        "DOI": "10.1016/j.jesp.2013.07.006",
        "article-title": "When stepping outside the self is not enough: A self-distanced perspective reduces the experience of basic but not of self-conscious emotions",
        "volume": "49",
        "author": "Katzir",
        "year": "2013",
        "journal-title": "Journal of Experimental Social Psychology"
      },
      {
        "key": "10.1016/j.concog.2021.103140_b0235",
        "doi-asserted-by": "crossref",
        "first-page": "18",
        "DOI": "10.1016/j.biopsych.2013.09.006",
        "article-title": "Gene × environment interaction studies have not properly controlled forpotential confounders: The problem and the (simple) solution",
        "volume": "75",
        "author": "Keller",
        "year": "2014",
        "journal-title": "Biological Psychiatry"
      },
      {
        "key": "10.1016/j.concog.2021.103140_b0240",
        "doi-asserted-by": "crossref",
        "first-page": "849",
        "DOI": "10.1037/a0019842",
        "article-title": "Control and interference in task switching: A review",
        "volume": "136",
        "author": "Kiesel",
        "year": "2010",
        "journal-title": "Psychological Bulletin"
      },
      {
        "key": "10.1016/j.concog.2021.103140_b0245",
        "doi-asserted-by": "crossref",
        "first-page": "68",
        "DOI": "10.1037/a0021466",
        "article-title": "Shame, guilt, and depressive symptoms: A meta-analytic review",
        "volume": "137",
        "author": "Kim",
        "year": "2011",
        "journal-title": "Psychological Bulletin"
      },
      {
        "key": "10.1016/j.concog.2021.103140_b0250",
        "first-page": "129",
        "article-title": "Digging deeper: The fundamental nature of “self-conscious” emotions",
        "volume": "15",
        "author": "Leary",
        "year": "2004",
        "journal-title": "Psychological Inquiry"
      },
      {
        "key": "10.1016/j.concog.2021.103140_b0255",
        "doi-asserted-by": "crossref",
        "first-page": "1",
        "DOI": "10.1111/1467-6494.00001",
        "article-title": "Empathy, shame, guilt, and narratives of interpersonal conflicts: Guilt-prone people are better at perspective taking",
        "volume": "66",
        "author": "Leith",
        "year": "1998",
        "journal-title": "Journal of Personality"
      },
      {
        "key": "10.1016/j.concog.2021.103140_b0260",
        "series-title": "The role of shame in symptom formation",
        "first-page": "29",
        "article-title": "The role of shame in depression over the life span",
        "author": "Lewis",
        "year": "1987"
      },
      {
        "key": "10.1016/j.concog.2021.103140_b0265",
        "doi-asserted-by": "crossref",
        "first-page": "1049",
        "DOI": "10.1037/a0038235",
        "article-title": "Shame and the motivation to change the self",
        "volume": "14",
        "author": "Lickel",
        "year": "2014",
        "journal-title": "Emotion"
      },
      {
        "key": "10.1016/j.concog.2021.103140_b0270",
        "doi-asserted-by": "crossref",
        "first-page": "376",
        "DOI": "10.1037/0033-2909.114.2.376",
        "article-title": "Statistical difficulties of detecting interactions and moderator effects",
        "volume": "114",
        "author": "McClelland",
        "year": "1993",
        "journal-title": "Psychological Bulletin"
      },
      {
        "key": "10.1016/j.concog.2021.103140_b0275",
        "doi-asserted-by": "crossref",
        "first-page": "172",
        "DOI": "10.1037/0033-2909.111.1.172",
        "article-title": "Comparing correlated correlation coefficients",
        "volume": "111",
        "author": "Meng",
        "year": "1992",
        "journal-title": "Psychological Bulletin"
      },
      {
        "key": "10.1016/j.concog.2021.103140_b0280",
        "doi-asserted-by": "crossref",
        "first-page": "881",
        "DOI": "10.1037/0022-3514.83.4.881",
        "article-title": "Activation of the attachment system in adulthood: Threat-related primes increase the accessibility of mental representations of attachment figures",
        "volume": "83",
        "author": "Mikulincer",
        "year": "2002",
        "journal-title": "Journal of Personality and Social Psychology"
      },
      {
        "key": "10.1016/j.concog.2021.103140_b0285",
        "doi-asserted-by": "crossref",
        "first-page": "134",
        "DOI": "10.1016/S1364-6613(03)00028-7",
        "article-title": "Task switching",
        "volume": "7",
        "author": "Monsell",
        "year": "2003",
        "journal-title": "Trends in Cognitive Sciences"
      },
      {
        "key": "10.1016/j.concog.2021.103140_b0290",
        "doi-asserted-by": "crossref",
        "first-page": "19",
        "DOI": "10.1007/s10567-013-0137-z",
        "article-title": "Small or big in the eyes of the other: On the developmental psychopathology of self-conscious emotions as shame, guilt, and pride",
        "volume": "17",
        "author": "Muris",
        "year": "2014",
        "journal-title": "Clinical Child and Family Psychology Review"
      },
      {
        "key": "10.1016/j.concog.2021.103140_b0295",
        "doi-asserted-by": "crossref",
        "first-page": "152",
        "DOI": "10.1016/j.tics.2011.01.005",
        "article-title": "Implicit social cognition: From measures to mechanisms",
        "volume": "15",
        "author": "Nosek",
        "year": "2011",
        "journal-title": "Trends in Cognitive Sciences"
      },
      {
        "key": "10.1016/j.concog.2021.103140_b0300",
        "doi-asserted-by": "crossref",
        "first-page": "65",
        "DOI": "10.1111/j.1467-8721.2007.00477.x",
        "article-title": "Implicit-explicit relations",
        "volume": "16",
        "author": "Nosek",
        "year": "2007",
        "journal-title": "Current Directions in Psychological Science"
      },
      {
        "key": "10.1016/j.concog.2021.103140_b0305",
        "doi-asserted-by": "crossref",
        "first-page": "254",
        "DOI": "10.1177/1073191102009003004",
        "article-title": "Dyadic short forms of the Wechsler Adult Intelligence Scale–III",
        "volume": "9",
        "author": "Ringe",
        "year": "2002",
        "journal-title": "Assessment"
      },
      {
        "key": "10.1016/j.concog.2021.103140_b0310",
        "doi-asserted-by": "crossref",
        "first-page": "207",
        "DOI": "10.1037/0096-3445.124.2.207",
        "article-title": "Costs of a predictable switch between simple cognitive tasks",
        "volume": "124",
        "author": "Rogers",
        "year": "1995",
        "journal-title": "Journal of Experimental Psychology: General"
      },
      {
        "key": "10.1016/j.concog.2021.103140_b0315",
        "first-page": "1255",
        "article-title": "Seeing it their way: Evidence for rapid and involuntary computation of what other people see",
        "volume": "36",
        "author": "Samson",
        "year": "2010",
        "journal-title": "Journal of Experimental Psychology: Human Perception and Performance"
      },
      {
        "key": "10.1016/j.concog.2021.103140_b0320",
        "first-page": "929",
        "article-title": "Avatars and arrows: Implicit mentalizing or domain-general processing?",
        "volume": "40",
        "author": "Santiesteban",
        "year": "2014",
        "journal-title": "Journal of Experimental Psychology: Human Perception and Performance"
      },
      {
        "key": "10.1016/j.concog.2021.103140_b0325",
        "doi-asserted-by": "crossref",
        "first-page": "305",
        "DOI": "10.1016/j.neuroimage.2017.04.055",
        "article-title": "Attentional processes, not implicit mentalizing, mediate performance in a perspective-taking task: Evidence from stimulation of the temporoparietal junction",
        "volume": "155",
        "author": "Santiesteban",
        "year": "2017",
        "journal-title": "NeuroImage"
      },
      {
        "key": "10.1016/j.concog.2021.103140_b0330",
        "doi-asserted-by": "crossref",
        "first-page": "98",
        "DOI": "10.1016/j.neuroimage.2018.05.016",
        "article-title": "Oscillatory networks of high-level mental alignment: A perspective-taking MEG study",
        "volume": "177",
        "author": "Seymour",
        "year": "2018",
        "journal-title": "NeuroImage"
      },
      {
        "key": "10.1016/j.concog.2021.103140_b0335",
        "doi-asserted-by": "crossref",
        "first-page": "199",
        "DOI": "10.1037/a0024617",
        "article-title": "Should social savvy equal good spatial skills? The interaction of social skills with spatial perspective taking",
        "volume": "141",
        "author": "Shelton",
        "year": "2012",
        "journal-title": "Journal of Experimental Psychology: General"
      },
      {
        "key": "10.1016/j.concog.2021.103140_b0340",
        "doi-asserted-by": "crossref",
        "first-page": "510",
        "DOI": "10.1177/1094428108320370",
        "article-title": "Detecting interaction effects in moderated multiple regression with continuous variables: Power and sample size considerations",
        "volume": "12",
        "author": "Shieh",
        "year": "2009",
        "journal-title": "Organizational Research Method"
      },
      {
        "key": "10.1016/j.concog.2021.103140_b0345",
        "doi-asserted-by": "crossref",
        "first-page": "426",
        "DOI": "10.1016/j.cognition.2013.06.008",
        "article-title": "Similarities and differences in visual and spatial perspective-taking processes",
        "volume": "129",
        "author": "Surtees",
        "year": "2013",
        "journal-title": "Cognition"
      },
      {
        "year": "2000",
        "series-title": "The test of self-conscious affect–3 (TOSCA-3)",
        "author": "Tangney",
        "key": "10.1016/j.concog.2021.103140_b0350"
      },
      {
        "key": "10.1016/j.concog.2021.103140_bib406",
        "doi-asserted-by": "crossref",
        "first-page": "102",
        "DOI": "10.1037/0022-3514.59.1.102",
        "article-title": "Assessing individual differences in proneness to shame and guilt: Development of the Self-Conscious Affect and Attribution Inventory",
        "volume": "59",
        "author": "Tangney",
        "year": "1990",
        "journal-title": "Journal of Personality and Social Psychology"
      },
      {
        "key": "10.1016/j.concog.2021.103140_b0355",
        "doi-asserted-by": "crossref",
        "first-page": "598",
        "DOI": "10.1037/0022-3514.61.4.598",
        "article-title": "Moral affect: The good, the bad, and the ugly",
        "volume": "61",
        "author": "Tangney",
        "year": "1991",
        "journal-title": "Journal of Personality and Social Psychology"
      },
      {
        "key": "10.1016/j.concog.2021.103140_b0360",
        "doi-asserted-by": "crossref",
        "first-page": "1256",
        "DOI": "10.1037/0022-3514.70.6.1256",
        "article-title": "Are shame, guilt, and embarrassment distinct emotions?",
        "volume": "70",
        "author": "Tangney",
        "year": "1996",
        "journal-title": "Journal of Personality and Social Psychology"
      },
      {
        "key": "10.1016/j.concog.2021.103140_b0365",
        "doi-asserted-by": "crossref",
        "first-page": "345",
        "DOI": "10.1146/annurev.psych.56.091103.070145",
        "article-title": "Moral emotions and moral behavior",
        "volume": "58",
        "author": "Tangney",
        "year": "2006",
        "journal-title": "Annual Review of Psychology"
      },
      {
        "key": "10.1016/j.concog.2021.103140_b0370",
        "doi-asserted-by": "crossref",
        "first-page": "469",
        "DOI": "10.1037/0021-843X.101.3.469",
        "article-title": "Proneness to shame, proneness to guilt, and psychopathology",
        "volume": "101",
        "author": "Tangney",
        "year": "1992",
        "journal-title": "Journal of Abnormal Psychology"
      },
      {
        "key": "10.1016/j.concog.2021.103140_b0375",
        "doi-asserted-by": "crossref",
        "first-page": "63",
        "DOI": "10.1007/s10802-006-9084-1",
        "article-title": "Development of social anxiety: Social interaction predictors of implicit and explicit fear of negative evaluation",
        "volume": "35",
        "author": "Teachman",
        "year": "2007",
        "journal-title": "Journal of Abnormal Child Psychology"
      },
      {
        "key": "10.1016/j.concog.2021.103140_b0380",
        "doi-asserted-by": "crossref",
        "first-page": "341",
        "DOI": "10.1111/jopy.12244",
        "article-title": "The interpersonal adaptiveness of dispositional guilt and shame: A meta-analytic investigation",
        "volume": "85",
        "author": "Tignor",
        "year": "2017",
        "journal-title": "Journal of Personality"
      },
      {
        "key": "10.1016/j.concog.2021.103140_b0385",
        "doi-asserted-by": "crossref",
        "first-page": "103",
        "DOI": "10.1207/s15327965pli1502_01",
        "article-title": "Putting the self into self-conscious emotions: A theoretical model",
        "volume": "15",
        "author": "Tracy",
        "year": "2004",
        "journal-title": "Psychological Inquiry"
      },
      {
        "issue": "8",
        "key": "10.1016/j.concog.2021.103140_b0390",
        "doi-asserted-by": "crossref",
        "first-page": "1504",
        "DOI": "10.1080/02699931.2015.1072497",
        "article-title": "Shame, guilt, and facial emotion processing: Initial evidence for a positive relationship between guilt-proneness and facial emotion recognition ability",
        "volume": "30",
        "author": "Treeby",
        "year": "2016",
        "journal-title": "Cognition and Emotion"
      },
      {
        "key": "10.1016/j.concog.2021.103140_b0395",
        "doi-asserted-by": "crossref",
        "first-page": "197",
        "DOI": "10.1177/0963721411409007",
        "article-title": "Two mechanisms for simulating other minds: Dissociations between mirroring and self-projection",
        "volume": "20",
        "author": "Waytz",
        "year": "2011",
        "journal-title": "Current Directions in Psychological Science"
      },
      {
        "key": "10.1016/j.concog.2021.103140_b0400",
        "doi-asserted-by": "crossref",
        "unstructured": "Yeh, Y.-Y., Wang, C.-C., Cheng, S.-k., & Chiu, C.-D. (2021). Dissociation of posture remapping and cognitive load in level-2 perspective-taking. Cognition. Advance online publication. https://doi.org/10.1016/j.cognition.2021.104733.",
        "DOI": "10.1016/j.cognition.2021.104733"
      },
      {
        "key": "10.1016/j.concog.2021.103140_b0405",
        "doi-asserted-by": "crossref",
        "first-page": "813",
        "DOI": "10.1111/j.1467-9280.2009.02373.x",
        "article-title": "Neural responses to partner rejection cues",
        "volume": "20",
        "author": "Zayas",
        "year": "2009",
        "journal-title": "Psychological Science"
      }
    ],
    "container-title": [
      "Consciousness and Cognition"
    ],
    "original-title": [],
    "language": "en",
    "link": [
      {
        "URL": "https://api.elsevier.com/content/article/PII:S1053810021000660?httpAccept=text/xml",
        "content-type": "text/xml",
        "content-version": "vor",
        "intended-application": "text-mining"
      },
      {
        "URL": "https://api.elsevier.com/content/article/PII:S1053810021000660?httpAccept=text/plain",
        "content-type": "text/plain",
        "content-version": "vor",
        "intended-application": "text-mining"
      }
    ],
    "deposited": {
      "date-parts": [
        [
          2025,
          10,
          20
        ]
      ],
      "date-time": "2025-10-20T09:25:09Z",
      "timestamp": 1760952309000
    },
    "score": 1,
    "resource": {
      "primary": {
        "URL": "https://linkinghub.elsevier.com/retrieve/pii/S1053810021000660"
      }
    },
    "subtitle": [],
    "short-title": [],
    "issued": {
      "date-parts": [
        [
          2021,
          7
        ]
      ]
    },
    "references-count": 82,
    "alternative-id": [
      "S1053810021000660"
    ],
    "URL": "https://doi.org/10.1016/j.concog.2021.103140",
    "relation": {},
    "ISSN": [
      "1053-8100"
    ],
    "issn-type": [
      {
        "type": "print",
        "value": "1053-8100"
      }
    ],
    "subject": [],
    "published": {
      "date-parts": [
        [
          2021,
          7
        ]
      ]
    },
    "assertion": [
      {
        "value": "Elsevier",
        "name": "publisher",
        "label": "This article is maintained by"
      },
      {
        "value": "Visuospatial perspective shifting and relational self-association in dispositional shame and guilt",
        "name": "articletitle",
        "label": "Article Title"
      },
      {
        "value": "Consciousness and Cognition",
        "name": "journaltitle",
        "label": "Journal Title"
      },
      {
        "value": "https://doi.org/10.1016/j.concog.2021.103140",
        "name": "articlelink",
        "label": "CrossRef DOI link to publisher maintained version"
      },
      {
        "value": "article",
        "name": "content_type",
        "label": "Content Type"
      },
      {
        "value": "© 2021 Elsevier Inc. All rights reserved.",
        "name": "copyright",
        "label": "Copyright"
      }
    ],
    "article-number": "103140"
  },
  "timestamp": 1767207481333,
  "ttl": 2592000000,
  "source": "crossref"
}